[
  {
    "label": "The Daily Prophet",
    "items": [
      {
        "title": "\u201cHarry Potter and the Cursed Child\u201d Actress Ebony Blake Dies After Cancer Treatment",
        "link": "https://mugglenet.com/2026/06/ebony-blake-harry-potter-cursed-child-actress-dies/",
        "date": "22 Jun"
      },
      {
        "title": "Nick Frost Knows His Hagrid in the New \u201cHarry Potter\u201d Series May Take Some Getting Used To",
        "link": "https://mugglenet.com/2026/06/nick-frost-hagrid-hbo-harry-potter-series/",
        "date": "21 Jun"
      },
      {
        "title": "Le Cirque Arcanus Closing Temporarily in Epic Universe\u2019s Harry Potter Land",
        "link": "https://mugglenet.com/2026/06/harry-potter-epic-universe-le-cirque-arcanus-closure/",
        "date": "20 Jun"
      },
      {
        "title": "Peter Serafinowicz Cast as Peeves in HBO\u2019s \u201cHarry Potter\u201d Series",
        "link": "https://mugglenet.com/2026/06/peter-serafinowicz-peeves-harry-potter-series/",
        "date": "15 Jun"
      },
      {
        "title": "New Epic Universe Nighttime Show Will Bring Harry Potter Magic to the Park",
        "link": "https://mugglenet.com/2026/06/universal-epic-universe-nighttime-show-harry-potter-ministry-magic/",
        "date": "15 Jun"
      }
    ]
  },
  {
    "label": "Disney News",
    "items": [
      {
        "title": "Custom Hidden Mickey Scepters Restocked at Crystal Arts in Magic Kingdom",
        "link": "https://wdwnt.com/2026/06/custom-hidden-mickey-scepters-restocked-at-crystal-arts-in-magic-kingdom/?adt_ei=*|EMAIL|*",
        "date": "22 Jun"
      },
      {
        "title": "The Hidden Perk at the EPCOT Food & Wine Festival",
        "link": "https://www.disneyfoodblog.com/2026/06/22/the-hidden-perk-at-the-epcot-food-wine-festival/",
        "date": "22 Jun"
      },
      {
        "title": "People Are Loving Disney\u2019s \u2018Toy Story 5\u2019 And These Numbers Are Proof",
        "link": "https://www.disneyfoodblog.com/2026/06/22/people-are-loving-disneys-toy-story-5-and-these-numbers-are-proof/",
        "date": "22 Jun"
      },
      {
        "title": "Target Circle Deal Days Starts TOMORROW! Here Are The 4 Best Things To Buy",
        "link": "https://www.disneyfoodblog.com/2026/06/22/target-circle-deal-days-starts-tomorrow-here-are-the-4-best-things-to-buy/",
        "date": "22 Jun"
      },
      {
        "title": "VIDEO: Epic Universe Testing 'Celestial Goodnight' Fireworks",
        "link": "https://wdwnt.com/2026/06/video-epic-universe-testing-celestial-goodnight-fireworks/?adt_ei=*|EMAIL|*",
        "date": "22 Jun"
      }
    ]
  }
]