[
  {
    "label": "The Daily Prophet",
    "items": [
      {
        "title": "Tom Felton Extends Broadway Run as Draco Malfoy Through November 2026",
        "link": "https://mugglenet.com/2026/04/tom-felton-extends-broadway-run-as-draco-malfoy-through-november-2026/",
        "date": "7 Apr"
      },
      {
        "title": "HBO Announces Harry Potter TV Series Doc, Finding Harry: The Craft Behind the Magic",
        "link": "https://mugglenet.com/2026/04/hbo-announces-harry-potter-tv-series-doc-finding-harry-the-craft-behind-the-magic/",
        "date": "2 Apr"
      },
      {
        "title": "Watch the First Trailer for HBO\u2019s upcoming \u2018Harry Potter\u2019 TV Series",
        "link": "https://mugglenet.com/2026/03/watch-the-first-trailer-for-hbos-upcoming-harry-potter-tv-series/",
        "date": "25 Mar"
      },
      {
        "title": "The Wait for the Harry Potter Series Trailer Has Fans Refreshing Nonstop",
        "link": "https://mugglenet.com/2026/03/the-wait-for-the-harry-potter-series-trailer-has-fans-refreshing-nonstop/",
        "date": "25 Mar"
      },
      {
        "title": "HBO Unveils the First Image from Its New Harry Potter TV Series",
        "link": "https://mugglenet.com/2026/03/first-hbo-still-harry-potter/",
        "date": "24 Mar"
      }
    ]
  },
  {
    "label": "Disney News",
    "items": [
      {
        "title": "Animal Enrichment for the 25th Anniversary of Animal Kingdom Lodge",
        "link": "https://wdwnt.com/2026/04/animal-enrichment-for-the-25th-anniversary-of-animal-kingdom-lodge/?adt_ei=*|EMAIL|*",
        "date": "18 Apr"
      },
      {
        "title": "32 Disney LEGO Sets are ON SALE Up to 50% Off on Amazon!",
        "link": "https://www.disneyfoodblog.com/2026/04/18/32-disney-lego-sets-are-on-sale-up-to-50-off-on-amazon/",
        "date": "18 Apr"
      },
      {
        "title": "Disney\u2019s Wilderness Lodge Dock Closed for Refurbishment, Painting Continues",
        "link": "https://wdwnt.com/2026/04/disneys-wilderness-lodge-dock-closed-painting-continues/?adt_ei=*|EMAIL|*",
        "date": "18 Apr"
      },
      {
        "title": "Free Water Park Perk Returning to Walt Disney World in 2027 But With Resort Exclusion in Today\u2019s Daily Recap for 4/17/2026",
        "link": "https://wdwnt.com/2026/04/free-water-park-perk-returning-to-walt-disney-world-in-2027-but-with-resort-exclusion-in-todays-daily-recap-for-4-17-2026/?adt_ei=*|EMAIL|*",
        "date": "18 Apr"
      },
      {
        "title": "Pandora Releases Disney Park Exclusive Lab-Grown Diamond Charm",
        "link": "https://wdwnt.com/2026/04/pandora-releases-disney-park-exclusive-lab-grown-diamond-charm/?adt_ei=*|EMAIL|*",
        "date": "18 Apr"
      }
    ]
  }
]