[
  {
    "label": "The Daily Prophet",
    "items": []
  },
  {
    "label": "Disney News",
    "items": [
      {
        "title": "Universal Confirms Use of Photo Validation for Individual Epic Universe Portal Entry at Select Times",
        "link": "https://wdwnt.com/2026/04/universal-confirms-use-of-photo-validation-for-individual-epic-universe-portal-entry-at-select-times/?adt_ei=*|EMAIL|*",
        "date": "21 Apr"
      },
      {
        "title": "Disney World Essentials Are Up to 50% OFF On Amazon Today",
        "link": "https://www.disneyfoodblog.com/2026/04/21/disney-world-essentials-are-up-to-50-off-on-amazon-today/",
        "date": "21 Apr"
      },
      {
        "title": "Tokyo Disney Resort Summer Cool-Off 2026 Dates & Details",
        "link": "https://wdwnt.com/2026/04/tokyo-disney-resort-summer-cool-off-2026-dates-details/?adt_ei=*|EMAIL|*",
        "date": "21 Apr"
      },
      {
        "title": "REVIEW: We Were SHOCKED by How Much We LOVED This New Universal Snack!",
        "link": "https://www.disneyfoodblog.com/2026/04/21/review-we-were-shocked-by-how-much-we-loved-this-new-universal-snack/",
        "date": "21 Apr"
      },
      {
        "title": "LeapFrog Releasing Real-Life Lilypad from \u2018Toy Story 5\u2019",
        "link": "https://wdwnt.com/2026/04/leapfrog-releasing-real-life-lilypad-from-toy-story-5/?adt_ei=*|EMAIL|*",
        "date": "21 Apr"
      }
    ]
  }
]